{
  "fetched_at": "2026-05-01T11:02:00.613411",
  "source": "https://recorder.maricopa.gov/recording/document-search.html",
  "date_range": {
    "start": "04/30/2026",
    "end": "04/30/2026"
  },
  "total": 26,
  "with_address": 23,
  "records": [
    {
      "doc_num": "20260258642",
      "doc_type": "N/TR SALE",
      "filed": "2026-04-30",
      "cat": "NS",
      "cat_label": "Notice of Trustee Sale",
      "owner": "",
      "grantee": "",
      "amount": "",
      "legal": "",
      "prop_address": "",
      "prop_city": "",
      "prop_state": "",
      "prop_zip": "",
      "mail_address": "",
      "mail_city": "",
      "mail_state": "",
      "mail_zip": "",
      "county": "Maricopa",
      "parcel_number": "",
      "original_loan": "",
      "trustee_name": "",
      "trustee_phone": "",
      "auction_date": "",
      "deed_of_trust": "",
      "first_name": "",
      "last_name": "",
      "second_first": "",
      "second_last": "",
      "clerk_url": "",
      "pdf_url": "https://legacy.recorder.maricopa.gov/UnOfficialDocs/pdf/20260258642.pdf",
      "pdf_path": "",
      "flags": [
        "pdf_blocked"
      ],
      "score": 0,
      "raw_text_path": ""
    },
    {
      "doc_num": "20260259295",
      "doc_type": "N/TR SALE",
      "filed": "2026-04-30",
      "cat": "NS",
      "cat_label": "Notice of Trustee Sale",
      "owner": "(as shown on the Deed of Trust): Sandra Jane Schwandt",
      "grantee": "",
      "amount": "170,000.00",
      "legal": "",
      "prop_address": "5114 N 83RD ST",
      "prop_city": "Scottsdale",
      "prop_state": "AZ",
      "prop_zip": "85250",
      "mail_address": "",
      "mail_city": "",
      "mail_state": "",
      "mail_zip": "",
      "county": "Maricopa",
      "parcel_number": "176-26-008",
      "original_loan": "",
      "trustee_name": "Barrett Daffin Frappier Treder & Weiss, Llp",
      "trustee_phone": "(855) 286-5901",
      "auction_date": "2026-08-06",
      "deed_of_trust": "",
      "first_name": "(as shown on the Deed of Trust): Sandra Jane",
      "last_name": "Schwandt",
      "second_first": "",
      "second_last": "",
      "clerk_url": "",
      "pdf_url": "https://legacy.recorder.maricopa.gov/UnOfficialDocs/pdf/20260259295.pdf",
      "pdf_path": "/home/runner/work/Chat-Scraper/Chat-Scraper/grouped_output/pdfs/20260259295.pdf",
      "flags": [
        "ocr_used"
      ],
      "score": 100,
      "raw_text_path": "/home/runner/work/Chat-Scraper/Chat-Scraper/parsed_output/20260259295.txt"
    },
    {
      "doc_num": "20260259334",
      "doc_type": "N/TR SALE",
      "filed": "2026-04-30",
      "cat": "NS",
      "cat_label": "Notice of Trustee Sale",
      "owner": "(as shown on the Deed of Trust): Corinthia A. White, An",
      "grantee": "",
      "amount": "392,755.00",
      "legal": "",
      "prop_address": "2825 E PUEBLO AVE",
      "prop_city": "Phoenix",
      "prop_state": "AZ",
      "prop_zip": "85040",
      "mail_address": "",
      "mail_city": "",
      "mail_state": "",
      "mail_zip": "",
      "county": "Maricopa",
      "parcel_number": "122-17",
      "original_loan": "",
      "trustee_name": "Barrett Daffin Frappier Treder & Weiss, Llp",
      "trustee_phone": "(855) 286-5901",
      "auction_date": "2026-08-05",
      "deed_of_trust": "",
      "first_name": "(as shown on the Deed of Trust): Corinthia A. White,",
      "last_name": "An",
      "second_first": "",
      "second_last": "",
      "clerk_url": "",
      "pdf_url": "https://legacy.recorder.maricopa.gov/UnOfficialDocs/pdf/20260259334.pdf",
      "pdf_path": "/home/runner/work/Chat-Scraper/Chat-Scraper/grouped_output/pdfs/20260259334.pdf",
      "flags": [
        "ocr_used"
      ],
      "score": 100,
      "raw_text_path": "/home/runner/work/Chat-Scraper/Chat-Scraper/parsed_output/20260259334.txt"
    },
    {
      "doc_num": "20260259356",
      "doc_type": "N/TR SALE",
      "filed": "2026-04-30",
      "cat": "NS",
      "cat_label": "Notice of Trustee Sale",
      "owner": "(as shown on the Deed of Trust): Damon Reine And",
      "grantee": "",
      "amount": "337,500.00",
      "legal": "",
      "prop_address": "201 W. Jefferson Street",
      "prop_city": "Phoenix",
      "prop_state": "AZ",
      "prop_zip": "85003",
      "mail_address": "",
      "mail_city": "",
      "mail_state": "",
      "mail_zip": "",
      "county": "Maricopa",
      "parcel_number": "305-04-137-1",
      "original_loan": "",
      "trustee_name": "Barrett Daffin Frappier Treder & Weiss, Llp",
      "trustee_phone": "(855) 286-5901",
      "auction_date": "2026-08-06",
      "deed_of_trust": "",
      "first_name": "(as shown on the Deed of Trust): Damon Reine",
      "last_name": "And",
      "second_first": "",
      "second_last": "",
      "clerk_url": "",
      "pdf_url": "https://legacy.recorder.maricopa.gov/UnOfficialDocs/pdf/20260259356.pdf",
      "pdf_path": "/home/runner/work/Chat-Scraper/Chat-Scraper/grouped_output/pdfs/20260259356.pdf",
      "flags": [
        "ocr_used"
      ],
      "score": 100,
      "raw_text_path": "/home/runner/work/Chat-Scraper/Chat-Scraper/parsed_output/20260259356.txt"
    },
    {
      "doc_num": "20260259377",
      "doc_type": "N/TR SALE",
      "filed": "2026-04-30",
      "cat": "NS",
      "cat_label": "Notice of Trustee Sale",
      "owner": "(as shown on the Deed of Trust): Brandon D Borrego And",
      "grantee": "",
      "amount": "555,000.00",
      "legal": "",
      "prop_address": "2313 E ROCKLEDGE ROAD",
      "prop_city": "Phoenix",
      "prop_state": "AZ",
      "prop_zip": "85048",
      "mail_address": "",
      "mail_city": "",
      "mail_state": "",
      "mail_zip": "",
      "county": "Maricopa",
      "parcel_number": "301-75-108",
      "original_loan": "",
      "trustee_name": "Barrett Daffin Frappier Treder & Weiss, Llp",
      "trustee_phone": "(855) 286-5901",
      "auction_date": "2024-08-27",
      "deed_of_trust": "",
      "first_name": "(as shown on the Deed of Trust): Brandon D Borrego",
      "last_name": "And",
      "second_first": "",
      "second_last": "",
      "clerk_url": "",
      "pdf_url": "https://legacy.recorder.maricopa.gov/UnOfficialDocs/pdf/20260259377.pdf",
      "pdf_path": "/home/runner/work/Chat-Scraper/Chat-Scraper/grouped_output/pdfs/20260259377.pdf",
      "flags": [
        "ocr_used"
      ],
      "score": 100,
      "raw_text_path": "/home/runner/work/Chat-Scraper/Chat-Scraper/parsed_output/20260259377.txt"
    },
    {
      "doc_num": "20260259526",
      "doc_type": "N/TR SALE",
      "filed": "2026-04-30",
      "cat": "NS",
      "cat_label": "Notice of Trustee Sale",
      "owner": "",
      "grantee": "",
      "amount": "149,000.00",
      "legal": "",
      "prop_address": "13415 W PORT ROYALE LN",
      "prop_city": "Surprise",
      "prop_state": "AZ",
      "prop_zip": "85379",
      "mail_address": "",
      "mail_city": "",
      "mail_state": "",
      "mail_zip": "",
      "county": "Maricopa",
      "parcel_number": "501-15-304",
      "original_loan": "",
      "trustee_name": "Mtc Financial Inc. dba Trustee Corps",
      "trustee_phone": "(200) 610-7382",
      "auction_date": "2024-08-29",
      "deed_of_trust": "",
      "first_name": "",
      "last_name": "",
      "second_first": "",
      "second_last": "",
      "clerk_url": "",
      "pdf_url": "https://legacy.recorder.maricopa.gov/UnOfficialDocs/pdf/20260259526.pdf",
      "pdf_path": "/home/runner/work/Chat-Scraper/Chat-Scraper/grouped_output/pdfs/20260259526.pdf",
      "flags": [
        "ocr_used",
        "missing_owner"
      ],
      "score": 75,
      "raw_text_path": "/home/runner/work/Chat-Scraper/Chat-Scraper/parsed_output/20260259526.txt"
    },
    {
      "doc_num": "20260259537",
      "doc_type": "N/TR SALE",
      "filed": "2026-04-30",
      "cat": "NS",
      "cat_label": "Notice of Trustee Sale",
      "owner": "",
      "grantee": "",
      "amount": "270,750.00",
      "legal": "",
      "prop_address": "",
      "prop_city": "",
      "prop_state": "",
      "prop_zip": "",
      "mail_address": "",
      "mail_city": "",
      "mail_state": "",
      "mail_zip": "",
      "county": "Maricopa",
      "parcel_number": "501-70-298",
      "original_loan": "",
      "trustee_name": "Mtc Financial Inc. dba Trustee Corps",
      "trustee_phone": "(202) 300-2902",
      "auction_date": "2024-08-29",
      "deed_of_trust": "",
      "first_name": "",
      "last_name": "",
      "second_first": "",
      "second_last": "",
      "clerk_url": "",
      "pdf_url": "https://legacy.recorder.maricopa.gov/UnOfficialDocs/pdf/20260259537.pdf",
      "pdf_path": "/home/runner/work/Chat-Scraper/Chat-Scraper/grouped_output/pdfs/20260259537.pdf",
      "flags": [
        "ocr_used",
        "missing_owner",
        "missing_address"
      ],
      "score": 45,
      "raw_text_path": "/home/runner/work/Chat-Scraper/Chat-Scraper/parsed_output/20260259537.txt"
    },
    {
      "doc_num": "20260259874",
      "doc_type": "N/TR SALE",
      "filed": "2026-04-30",
      "cat": "NS",
      "cat_label": "Notice of Trustee Sale",
      "owner": "",
      "grantee": "",
      "amount": "192,500.00",
      "legal": "",
      "prop_address": "5144 WEST DESERT COVE AVENUE",
      "prop_city": "Glendale",
      "prop_state": "AZ",
      "prop_zip": "85304",
      "mail_address": "",
      "mail_city": "",
      "mail_state": "",
      "mail_zip": "",
      "county": "Maricopa",
      "parcel_number": "",
      "original_loan": "",
      "trustee_name": "Sale Or If You Have An Objection To The Trustee",
      "trustee_phone": "(202) 106-3568",
      "auction_date": "2026-08-13",
      "deed_of_trust": "",
      "first_name": "",
      "last_name": "",
      "second_first": "",
      "second_last": "",
      "clerk_url": "",
      "pdf_url": "https://legacy.recorder.maricopa.gov/UnOfficialDocs/pdf/20260259874.pdf",
      "pdf_path": "/home/runner/work/Chat-Scraper/Chat-Scraper/grouped_output/pdfs/20260259874.pdf",
      "flags": [
        "ocr_used",
        "missing_owner",
        "missing_apn"
      ],
      "score": 60,
      "raw_text_path": "/home/runner/work/Chat-Scraper/Chat-Scraper/parsed_output/20260259874.txt"
    },
    {
      "doc_num": "20260260018",
      "doc_type": "N/TR SALE",
      "filed": "2026-04-30",
      "cat": "NS",
      "cat_label": "Notice of Trustee Sale",
      "owner": "",
      "grantee": "",
      "amount": "104,000.00",
      "legal": "",
      "prop_address": "5122 E SHEA BLVD UNIT 2096",
      "prop_city": "Scottsdale",
      "prop_state": "AZ",
      "prop_zip": "85254",
      "mail_address": "",
      "mail_city": "",
      "mail_state": "",
      "mail_zip": "",
      "county": "Maricopa",
      "parcel_number": "",
      "original_loan": "",
      "trustee_name": "Sale Or If You Have An Objection To The Trustee",
      "trustee_phone": "(201) 600-9215",
      "auction_date": "2026-08-13",
      "deed_of_trust": "",
      "first_name": "",
      "last_name": "",
      "second_first": "",
      "second_last": "",
      "clerk_url": "",
      "pdf_url": "https://legacy.recorder.maricopa.gov/UnOfficialDocs/pdf/20260260018.pdf",
      "pdf_path": "/home/runner/work/Chat-Scraper/Chat-Scraper/grouped_output/pdfs/20260260018.pdf",
      "flags": [
        "ocr_used",
        "missing_owner",
        "missing_apn"
      ],
      "score": 60,
      "raw_text_path": "/home/runner/work/Chat-Scraper/Chat-Scraper/parsed_output/20260260018.txt"
    },
    {
      "doc_num": "20260260671",
      "doc_type": "N/TR SALE",
      "filed": "2026-04-30",
      "cat": "NS",
      "cat_label": "Notice of Trustee Sale",
      "owner": "",
      "grantee": "",
      "amount": "157,500.00",
      "legal": "",
      "prop_address": "2509 S 115TH DR",
      "prop_city": "Avondale",
      "prop_state": "AZ",
      "prop_zip": "85323",
      "mail_address": "",
      "mail_city": "",
      "mail_state": "",
      "mail_zip": "",
      "county": "Maricopa",
      "parcel_number": "",
      "original_loan": "",
      "trustee_name": "Sale Or If You Have An Objection To The Trustee",
      "trustee_phone": "(202) 106-7873",
      "auction_date": "2026-08-13",
      "deed_of_trust": "",
      "first_name": "",
      "last_name": "",
      "second_first": "",
      "second_last": "",
      "clerk_url": "",
      "pdf_url": "https://legacy.recorder.maricopa.gov/UnOfficialDocs/pdf/20260260671.pdf",
      "pdf_path": "/home/runner/work/Chat-Scraper/Chat-Scraper/grouped_output/pdfs/20260260671.pdf",
      "flags": [
        "ocr_used",
        "missing_owner",
        "missing_apn"
      ],
      "score": 60,
      "raw_text_path": "/home/runner/work/Chat-Scraper/Chat-Scraper/parsed_output/20260260671.txt"
    },
    {
      "doc_num": "20260260750",
      "doc_type": "N/TR SALE",
      "filed": "2026-04-30",
      "cat": "NS",
      "cat_label": "Notice of Trustee Sale",
      "owner": "Elliott Marko and Nicole Marko, husband and wife",
      "grantee": "",
      "amount": "647,200.00",
      "legal": "",
      "prop_address": "11441 E Rafael Ave",
      "prop_city": "Mesa",
      "prop_state": "AZ",
      "prop_zip": "85212",
      "mail_address": "",
      "mail_city": "",
      "mail_state": "",
      "mail_zip": "",
      "county": "Maricopa",
      "parcel_number": "304-33-794",
      "original_loan": "",
      "trustee_name": "",
      "trustee_phone": "(202) 206-8986",
      "auction_date": "",
      "deed_of_trust": "",
      "first_name": "Elliott",
      "last_name": "Marko",
      "second_first": "Nicole Marko, husband and",
      "second_last": "wife",
      "clerk_url": "",
      "pdf_url": "https://legacy.recorder.maricopa.gov/UnOfficialDocs/pdf/20260260750.pdf",
      "pdf_path": "/home/runner/work/Chat-Scraper/Chat-Scraper/grouped_output/pdfs/20260260750.pdf",
      "flags": [
        "ocr_used",
        "missing_trustee",
        "missing_auction_date"
      ],
      "score": 70,
      "raw_text_path": "/home/runner/work/Chat-Scraper/Chat-Scraper/parsed_output/20260260750.txt"
    },
    {
      "doc_num": "20260260781",
      "doc_type": "N/TR SALE",
      "filed": "2026-04-30",
      "cat": "NS",
      "cat_label": "Notice of Trustee Sale",
      "owner": "Bryan Wadman and Laura Wadman, husband and wife as community property with right of",
      "grantee": "",
      "amount": "647,200.00",
      "legal": "",
      "prop_address": "201 W. Jefferson Street",
      "prop_city": "Phoenix",
      "prop_state": "AZ",
      "prop_zip": "85003",
      "mail_address": "",
      "mail_city": "",
      "mail_state": "",
      "mail_zip": "",
      "county": "Maricopa",
      "parcel_number": "313-30-098",
      "original_loan": "",
      "trustee_name": "",
      "trustee_phone": "(202) 206-6905",
      "auction_date": "",
      "deed_of_trust": "",
      "first_name": "Bryan",
      "last_name": "Wadman",
      "second_first": "Laura Wadman, husband and wife as community property with right",
      "second_last": "of",
      "clerk_url": "",
      "pdf_url": "https://legacy.recorder.maricopa.gov/UnOfficialDocs/pdf/20260260781.pdf",
      "pdf_path": "/home/runner/work/Chat-Scraper/Chat-Scraper/grouped_output/pdfs/20260260781.pdf",
      "flags": [
        "ocr_used",
        "missing_trustee",
        "missing_auction_date"
      ],
      "score": 70,
      "raw_text_path": "/home/runner/work/Chat-Scraper/Chat-Scraper/parsed_output/20260260781.txt"
    },
    {
      "doc_num": "20260260814",
      "doc_type": "N/TR SALE",
      "filed": "2026-04-30",
      "cat": "NS",
      "cat_label": "Notice of Trustee Sale",
      "owner": "Erika Silva, a married woman as her sole and separate property",
      "grantee": "",
      "amount": "243,750.00",
      "legal": "",
      "prop_address": "7340 W. Bethany Home Rd.",
      "prop_city": "Glendale",
      "prop_state": "AZ",
      "prop_zip": "85303",
      "mail_address": "",
      "mail_city": "",
      "mail_state": "",
      "mail_zip": "",
      "county": "Maricopa",
      "parcel_number": "144-03-223",
      "original_loan": "",
      "trustee_name": "",
      "trustee_phone": "(202) 201-4002",
      "auction_date": "2026-11-03",
      "deed_of_trust": "",
      "first_name": "Erika Silva, a married woman as her",
      "last_name": "sole",
      "second_first": "separate",
      "second_last": "property",
      "clerk_url": "",
      "pdf_url": "https://legacy.recorder.maricopa.gov/UnOfficialDocs/pdf/20260260814.pdf",
      "pdf_path": "/home/runner/work/Chat-Scraper/Chat-Scraper/grouped_output/pdfs/20260260814.pdf",
      "flags": [
        "ocr_used",
        "missing_trustee"
      ],
      "score": 80,
      "raw_text_path": "/home/runner/work/Chat-Scraper/Chat-Scraper/parsed_output/20260260814.txt"
    },
    {
      "doc_num": "20260260921",
      "doc_type": "N/TR SALE",
      "filed": "2026-04-30",
      "cat": "NS",
      "cat_label": "Notice of Trustee Sale",
      "owner": "",
      "grantee": "",
      "amount": "269,920.00",
      "legal": "",
      "prop_address": "11570 W COCOPAH ST",
      "prop_city": "Avondale",
      "prop_state": "AZ",
      "prop_zip": "85323",
      "mail_address": "",
      "mail_city": "",
      "mail_state": "",
      "mail_zip": "",
      "county": "Maricopa",
      "parcel_number": "500-30-338",
      "original_loan": "",
      "trustee_name": "will require any entity or trust bidder at this trustee's sale to provide beneficial",
      "trustee_phone": "(844) 693-4761",
      "auction_date": "2026-08-04",
      "deed_of_trust": "",
      "first_name": "",
      "last_name": "",
      "second_first": "",
      "second_last": "",
      "clerk_url": "",
      "pdf_url": "https://legacy.recorder.maricopa.gov/UnOfficialDocs/pdf/20260260921.pdf",
      "pdf_path": "/home/runner/work/Chat-Scraper/Chat-Scraper/grouped_output/pdfs/20260260921.pdf",
      "flags": [
        "ocr_used",
        "missing_owner"
      ],
      "score": 75,
      "raw_text_path": "/home/runner/work/Chat-Scraper/Chat-Scraper/parsed_output/20260260921.txt"
    },
    {
      "doc_num": "20260260922",
      "doc_type": "N/TR SALE",
      "filed": "2026-04-30",
      "cat": "NS",
      "cat_label": "Notice of Trustee Sale",
      "owner": "",
      "grantee": "",
      "amount": "235,653.00",
      "legal": "",
      "prop_address": "1575 S 173RD DR",
      "prop_city": "Goodyear",
      "prop_state": "AZ",
      "prop_zip": "85338",
      "mail_address": "",
      "mail_city": "",
      "mail_state": "",
      "mail_zip": "",
      "county": "Maricopa",
      "parcel_number": "502-43-409",
      "original_loan": "",
      "trustee_name": "will require any entity or trust bidder at this trustee's sale to provide beneficial",
      "trustee_phone": "(844) 693-4761",
      "auction_date": "2026-08-04",
      "deed_of_trust": "",
      "first_name": "",
      "last_name": "",
      "second_first": "",
      "second_last": "",
      "clerk_url": "",
      "pdf_url": "https://legacy.recorder.maricopa.gov/UnOfficialDocs/pdf/20260260922.pdf",
      "pdf_path": "/home/runner/work/Chat-Scraper/Chat-Scraper/grouped_output/pdfs/20260260922.pdf",
      "flags": [
        "ocr_used",
        "missing_owner"
      ],
      "score": 75,
      "raw_text_path": "/home/runner/work/Chat-Scraper/Chat-Scraper/parsed_output/20260260922.txt"
    },
    {
      "doc_num": "20260260933",
      "doc_type": "N/TR SALE",
      "filed": "2026-04-30",
      "cat": "NS",
      "cat_label": "Notice of Trustee Sale",
      "owner": "(s): Gordon Mccann And Allison Mccann",
      "grantee": "",
      "amount": "479,150.00",
      "legal": "",
      "prop_address": "2805 N 192ND AVE",
      "prop_city": "Buckeye",
      "prop_state": "AZ",
      "prop_zip": "85396",
      "mail_address": "",
      "mail_city": "",
      "mail_state": "",
      "mail_zip": "",
      "county": "Maricopa",
      "parcel_number": "502-66-00534",
      "original_loan": "",
      "trustee_name": "Name and Address of Trustee/Agent: Quality Loan Service Corporation",
      "trustee_phone": "(202) 005-8155",
      "auction_date": "2026-08-06",
      "deed_of_trust": "",
      "first_name": "(s): Gordon Mccann And Allison",
      "last_name": "Mccann",
      "second_first": "",
      "second_last": "",
      "clerk_url": "",
      "pdf_url": "https://legacy.recorder.maricopa.gov/UnOfficialDocs/pdf/20260260933.pdf",
      "pdf_path": "/home/runner/work/Chat-Scraper/Chat-Scraper/grouped_output/pdfs/20260260933.pdf",
      "flags": [
        "ocr_used"
      ],
      "score": 100,
      "raw_text_path": "/home/runner/work/Chat-Scraper/Chat-Scraper/parsed_output/20260260933.txt"
    },
    {
      "doc_num": "20260260935",
      "doc_type": "N/TR SALE",
      "filed": "2026-04-30",
      "cat": "NS",
      "cat_label": "Notice of Trustee Sale",
      "owner": "",
      "grantee": "",
      "amount": "366,300.00",
      "legal": "",
      "prop_address": "or identifiable location: 24636 W HOPI STREET",
      "prop_city": "Buckeye",
      "prop_state": "AZ",
      "prop_zip": "85326",
      "mail_address": "",
      "mail_city": "",
      "mail_state": "",
      "mail_zip": "",
      "county": "Maricopa",
      "parcel_number": "504-65-239",
      "original_loan": "",
      "trustee_name": "Sale Or If You Have An Objection To The Trustee Sale, You Must File An",
      "trustee_phone": "(202) 501-6921",
      "auction_date": "2025-03-26",
      "deed_of_trust": "2025-03-26",
      "first_name": "",
      "last_name": "",
      "second_first": "",
      "second_last": "",
      "clerk_url": "",
      "pdf_url": "https://legacy.recorder.maricopa.gov/UnOfficialDocs/pdf/20260260935.pdf",
      "pdf_path": "/home/runner/work/Chat-Scraper/Chat-Scraper/grouped_output/pdfs/20260260935.pdf",
      "flags": [
        "ocr_used",
        "missing_owner"
      ],
      "score": 75,
      "raw_text_path": "/home/runner/work/Chat-Scraper/Chat-Scraper/parsed_output/20260260935.txt"
    },
    {
      "doc_num": "20260260936",
      "doc_type": "N/TR SALE",
      "filed": "2026-04-30",
      "cat": "NS",
      "cat_label": "Notice of Trustee Sale",
      "owner": "(s): Robert W. Marler, an unmarried man",
      "grantee": "",
      "amount": "113,500.00",
      "legal": "",
      "prop_address": "548 E GLENCOVE ST",
      "prop_city": "Mesa",
      "prop_state": "AZ",
      "prop_zip": "85203",
      "mail_address": "",
      "mail_city": "",
      "mail_state": "",
      "mail_zip": "",
      "county": "Maricopa",
      "parcel_number": "136-26-743",
      "original_loan": "",
      "trustee_name": "Name and Address of Trustee/Agent: Quality Loan Service Corporation",
      "trustee_phone": "(202) 106-1629",
      "auction_date": "2026-08-06",
      "deed_of_trust": "",
      "first_name": "(s): Robert W. Marler, an unmarried",
      "last_name": "man",
      "second_first": "",
      "second_last": "",
      "clerk_url": "",
      "pdf_url": "https://legacy.recorder.maricopa.gov/UnOfficialDocs/pdf/20260260936.pdf",
      "pdf_path": "/home/runner/work/Chat-Scraper/Chat-Scraper/grouped_output/pdfs/20260260936.pdf",
      "flags": [
        "ocr_used"
      ],
      "score": 100,
      "raw_text_path": "/home/runner/work/Chat-Scraper/Chat-Scraper/parsed_output/20260260936.txt"
    },
    {
      "doc_num": "20260261008",
      "doc_type": "N/TR SALE",
      "filed": "2026-04-30",
      "cat": "NS",
      "cat_label": "Notice of Trustee Sale",
      "owner": "",
      "grantee": "",
      "amount": "324,022.00",
      "legal": "",
      "prop_address": "11111 W HOLLYWOOD AVE",
      "prop_city": "Youngtown",
      "prop_state": "AZ",
      "prop_zip": "85363",
      "mail_address": "",
      "mail_city": "",
      "mail_state": "",
      "mail_zip": "",
      "county": "Maricopa",
      "parcel_number": "",
      "original_loan": "",
      "trustee_name": "Sale Or If You Have An Objection To The Trustee",
      "trustee_phone": "(202) 203-3702",
      "auction_date": "2026-08-13",
      "deed_of_trust": "",
      "first_name": "",
      "last_name": "",
      "second_first": "",
      "second_last": "",
      "clerk_url": "",
      "pdf_url": "https://legacy.recorder.maricopa.gov/UnOfficialDocs/pdf/20260261008.pdf",
      "pdf_path": "/home/runner/work/Chat-Scraper/Chat-Scraper/grouped_output/pdfs/20260261008.pdf",
      "flags": [
        "ocr_used",
        "missing_owner",
        "missing_apn"
      ],
      "score": 60,
      "raw_text_path": "/home/runner/work/Chat-Scraper/Chat-Scraper/parsed_output/20260261008.txt"
    },
    {
      "doc_num": "20260261834",
      "doc_type": "N/TR SALE",
      "filed": "2026-04-30",
      "cat": "NS",
      "cat_label": "Notice of Trustee Sale",
      "owner": "Derek Schultz, an unmarried man",
      "grantee": "",
      "amount": "372,875.00",
      "legal": "",
      "prop_address": "201 W. Jefferson Street",
      "prop_city": "Phoenix",
      "prop_state": "AZ",
      "prop_zip": "85003",
      "mail_address": "",
      "mail_city": "",
      "mail_state": "",
      "mail_zip": "",
      "county": "Maricopa",
      "parcel_number": "310-12-272",
      "original_loan": "",
      "trustee_name": "",
      "trustee_phone": "(202) 010-5320",
      "auction_date": "2026-11-03",
      "deed_of_trust": "",
      "first_name": "Derek Schultz, an unmarried",
      "last_name": "man",
      "second_first": "",
      "second_last": "",
      "clerk_url": "",
      "pdf_url": "https://legacy.recorder.maricopa.gov/UnOfficialDocs/pdf/20260261834.pdf",
      "pdf_path": "/home/runner/work/Chat-Scraper/Chat-Scraper/grouped_output/pdfs/20260261834.pdf",
      "flags": [
        "ocr_used",
        "missing_trustee"
      ],
      "score": 80,
      "raw_text_path": "/home/runner/work/Chat-Scraper/Chat-Scraper/parsed_output/20260261834.txt"
    },
    {
      "doc_num": "20260261837",
      "doc_type": "N/TR SALE",
      "filed": "2026-04-30",
      "cat": "NS",
      "cat_label": "Notice of Trustee Sale",
      "owner": "",
      "grantee": "",
      "amount": "181,649.00",
      "legal": "",
      "prop_address": "",
      "prop_city": "",
      "prop_state": "",
      "prop_zip": "",
      "mail_address": "",
      "mail_city": "",
      "mail_state": "",
      "mail_zip": "",
      "county": "Maricopa",
      "parcel_number": "220-17-137",
      "original_loan": "",
      "trustee_name": "before a trustee’s deed will be issued for covered",
      "trustee_phone": "(888) 403-4115",
      "auction_date": "2024-08-29",
      "deed_of_trust": "",
      "first_name": "",
      "last_name": "",
      "second_first": "",
      "second_last": "",
      "clerk_url": "",
      "pdf_url": "https://legacy.recorder.maricopa.gov/UnOfficialDocs/pdf/20260261837.pdf",
      "pdf_path": "/home/runner/work/Chat-Scraper/Chat-Scraper/grouped_output/pdfs/20260261837.pdf",
      "flags": [
        "ocr_used",
        "missing_owner",
        "missing_address"
      ],
      "score": 45,
      "raw_text_path": "/home/runner/work/Chat-Scraper/Chat-Scraper/parsed_output/20260261837.txt"
    },
    {
      "doc_num": "20260261841",
      "doc_type": "N/TR SALE",
      "filed": "2026-04-30",
      "cat": "NS",
      "cat_label": "Notice of Trustee Sale",
      "owner": "Steven A. Cooper, a single man",
      "grantee": "",
      "amount": "564,585.00",
      "legal": "",
      "prop_address": "2241 W Campbell Ave.",
      "prop_city": "Phoenix",
      "prop_state": "AZ",
      "prop_zip": "85015",
      "mail_address": "",
      "mail_city": "",
      "mail_state": "",
      "mail_zip": "",
      "county": "Maricopa",
      "parcel_number": "154-16",
      "original_loan": "",
      "trustee_name": "",
      "trustee_phone": "(202) 007-3810",
      "auction_date": "",
      "deed_of_trust": "",
      "first_name": "Steven A. Cooper, a single",
      "last_name": "man",
      "second_first": "",
      "second_last": "",
      "clerk_url": "",
      "pdf_url": "https://legacy.recorder.maricopa.gov/UnOfficialDocs/pdf/20260261841.pdf",
      "pdf_path": "/home/runner/work/Chat-Scraper/Chat-Scraper/grouped_output/pdfs/20260261841.pdf",
      "flags": [
        "ocr_used",
        "missing_trustee",
        "missing_auction_date"
      ],
      "score": 70,
      "raw_text_path": "/home/runner/work/Chat-Scraper/Chat-Scraper/parsed_output/20260261841.txt"
    },
    {
      "doc_num": "20260261865",
      "doc_type": "N/TR SALE",
      "filed": "2026-04-30",
      "cat": "NS",
      "cat_label": "Notice of Trustee Sale",
      "owner": "Sonoran Reems Holdings Llc, an Arizona limited",
      "grantee": "",
      "amount": "2,500,000.00",
      "legal": "",
      "prop_address": "2150 E. Brown Road, Ste 2 60",
      "prop_city": "Mesa",
      "prop_state": "AZ",
      "prop_zip": "85213",
      "mail_address": "",
      "mail_city": "",
      "mail_state": "",
      "mail_zip": "",
      "county": "Maricopa",
      "parcel_number": "204-13",
      "original_loan": "",
      "trustee_name": "Statewide Foreclosure Services, Inc., a",
      "trustee_phone": "(202) 303-1574",
      "auction_date": "2026-04-30",
      "deed_of_trust": "",
      "first_name": "Sonoran Reems Holdings Llc, an Arizona",
      "last_name": "limited",
      "second_first": "",
      "second_last": "",
      "clerk_url": "",
      "pdf_url": "https://legacy.recorder.maricopa.gov/UnOfficialDocs/pdf/20260261865.pdf",
      "pdf_path": "/home/runner/work/Chat-Scraper/Chat-Scraper/grouped_output/pdfs/20260261865.pdf",
      "flags": [
        "ocr_used"
      ],
      "score": 100,
      "raw_text_path": "/home/runner/work/Chat-Scraper/Chat-Scraper/parsed_output/20260261865.txt"
    },
    {
      "doc_num": "20260261900",
      "doc_type": "N/TR SALE",
      "filed": "2026-04-30",
      "cat": "NS",
      "cat_label": "Notice of Trustee Sale",
      "owner": "",
      "grantee": "",
      "amount": "380,962.00",
      "legal": "",
      "prop_address": "or identifiable location: 5743 WEST LODGE DRIVE",
      "prop_city": "Laveen",
      "prop_state": "AZ",
      "prop_zip": "85339",
      "mail_address": "",
      "mail_city": "",
      "mail_state": "",
      "mail_zip": "",
      "county": "Maricopa",
      "parcel_number": "300-19-243",
      "original_loan": "",
      "trustee_name": "Sale Or If You Have An Objection To The Trustee Sale, You Must File",
      "trustee_phone": "(888) 403-4115",
      "auction_date": "2024-08-29",
      "deed_of_trust": "",
      "first_name": "",
      "last_name": "",
      "second_first": "",
      "second_last": "",
      "clerk_url": "",
      "pdf_url": "https://legacy.recorder.maricopa.gov/UnOfficialDocs/pdf/20260261900.pdf",
      "pdf_path": "/home/runner/work/Chat-Scraper/Chat-Scraper/grouped_output/pdfs/20260261900.pdf",
      "flags": [
        "ocr_used",
        "missing_owner"
      ],
      "score": 75,
      "raw_text_path": "/home/runner/work/Chat-Scraper/Chat-Scraper/parsed_output/20260261900.txt"
    },
    {
      "doc_num": "20260261908",
      "doc_type": "N/TR SALE",
      "filed": "2026-04-30",
      "cat": "NS",
      "cat_label": "Notice of Trustee Sale",
      "owner": "",
      "grantee": "",
      "amount": "417,302.00",
      "legal": "",
      "prop_address": "or identifiable location: 5441 E. Flower Ave",
      "prop_city": "Mesa",
      "prop_state": "AZ",
      "prop_zip": "85206",
      "mail_address": "",
      "mail_city": "",
      "mail_state": "",
      "mail_zip": "",
      "county": "Maricopa",
      "parcel_number": "141-83-868",
      "original_loan": "",
      "trustee_name": "before a trustee’s deed will be issued for covered",
      "trustee_phone": "(888) 403-4115",
      "auction_date": "2025-11-03",
      "deed_of_trust": "",
      "first_name": "",
      "last_name": "",
      "second_first": "",
      "second_last": "",
      "clerk_url": "",
      "pdf_url": "https://legacy.recorder.maricopa.gov/UnOfficialDocs/pdf/20260261908.pdf",
      "pdf_path": "/home/runner/work/Chat-Scraper/Chat-Scraper/grouped_output/pdfs/20260261908.pdf",
      "flags": [
        "ocr_used",
        "missing_owner"
      ],
      "score": 75,
      "raw_text_path": "/home/runner/work/Chat-Scraper/Chat-Scraper/parsed_output/20260261908.txt"
    },
    {
      "doc_num": "20260262340",
      "doc_type": "N/TR SALE",
      "filed": "2026-04-30",
      "cat": "NS",
      "cat_label": "Notice of Trustee Sale",
      "owner": "",
      "grantee": "",
      "amount": "337,810.00",
      "legal": "",
      "prop_address": "or identifiable location: 30242 W PINCHOT AVE",
      "prop_city": "Buckeye",
      "prop_state": "AZ",
      "prop_zip": "85396",
      "mail_address": "",
      "mail_city": "",
      "mail_state": "",
      "mail_zip": "",
      "county": "Maricopa",
      "parcel_number": "504-74-701",
      "original_loan": "",
      "trustee_name": "Sale Or If You Have An Objection To The Trustee Sale, You Must File",
      "trustee_phone": "(202) 205-0197",
      "auction_date": "2026-08-11",
      "deed_of_trust": "2022-06-10",
      "first_name": "",
      "last_name": "",
      "second_first": "",
      "second_last": "",
      "clerk_url": "",
      "pdf_url": "https://legacy.recorder.maricopa.gov/UnOfficialDocs/pdf/20260262340.pdf",
      "pdf_path": "/home/runner/work/Chat-Scraper/Chat-Scraper/grouped_output/pdfs/20260262340.pdf",
      "flags": [
        "ocr_used",
        "missing_owner"
      ],
      "score": 75,
      "raw_text_path": "/home/runner/work/Chat-Scraper/Chat-Scraper/parsed_output/20260262340.txt"
    }
  ]
}